honey_board/__init__.py
honey_board/models/__init__.py
honey_board/models/hello_world/__init__.py
honey_board/models/hello_world/hello_world.py
honey_board/models/settings/__init__.py
honey_board/models/settings/config.py
honey_board/modules/__init__.py
honey_board/modules/logging/__init__.py
honey_board/modules/logging/logging.py
honey_board/modules/net_state_modules/__init__.py
honey_board/modules/net_state_modules/net_state_module.py
honey_board/modules/operation_timing_modules/__init__.py
honey_board/modules/operation_timing_modules/operation_timing.py
honey_board/modules/serializator/__init__.py
honey_board/modules/serializator/serializator.py
honey_board/modules/shell_starter_modules/__init__.py
honey_board/modules/shell_starter_modules/shell_starter_general_module.py
honey_board/modules/shell_starter_modules/shell_starter_module.py
honey_board/modules/shell_starter_modules/shell_starter_net_state_module.py
HoneyBoard-0.0.6.dist-info/LICENSE.txt
HoneyBoard-0.0.6.dist-info/METADATA
HoneyBoard-0.0.6.dist-info/WHEEL
HoneyBoard-0.0.6.dist-info/top_level.txt
HoneyBoard-0.0.6.dist-info/RECORD
