Metadata-Version: 2.1
Name: HoneyBoard
Version: 0.0.6
Summary: HoneyBoard
Home-page: https://github.com/vyadzmak/HoneyBoard
Author: Alex Hvedkovich
Author-email: a.hvedkovich@netvix.by
License: UNKNOWN
Project-URL: Source, https://github.com/vyadzmak/HoneyBoard.git
Keywords: honey board intelligence system
Platform: UNKNOWN
Classifier: Programming Language :: Python :: 3
Classifier: License :: OSI Approved :: MIT License
Classifier: Operating System :: OS Independent
Requires-Dist: PyYaml
Requires-Dist: click
Requires-Dist: coloredlogs
Requires-Dist: jsonpickle
